django_gravatar/__init__.py
django_gravatar/compat.py
django_gravatar/helpers.py
django_gravatar/models.py
django_gravatar/tests.py
django_gravatar/views.py
django_gravatar/templatetags/__init__.py
django_gravatar/templatetags/gravatar.py
example_project/__init__.py
example_project/manage.py
example_project/settings.py
django_gravatar2-1.4.3.dist-info/LICENSE
django_gravatar2-1.4.3.dist-info/METADATA
django_gravatar2-1.4.3.dist-info/WHEEL
django_gravatar2-1.4.3.dist-info/top_level.txt
django_gravatar2-1.4.3.dist-info/RECORD
