Metadata-Version: 2.1
Name: django-gravatar2
Version: 1.4.3
Summary: Essential Gravatar support for Django. Features helper methods, templatetags and a full test suite!
Home-page: https://github.com/twaddington/django-gravatar
Author: Tristan Waddington
Author-email: tristan.waddington@gmail.com
License: MIT
Keywords: django gravatar avatar
Platform: UNKNOWN
Classifier: Development Status :: 5 - Production/Stable
Classifier: Environment :: Web Environment
Classifier: Intended Audience :: Developers
Classifier: License :: OSI Approved :: MIT License
Classifier: Operating System :: OS Independent
Classifier: Programming Language :: Python
Classifier: Programming Language :: Python :: 2
Classifier: Programming Language :: Python :: 3
Classifier: Framework :: Django
